{
  "template": "mvd_prilozhenie_7",
  "template_version": "1",
  "mapping_version": "1",
  "page_size": [
    595.3,
    842.4
  ],
  "fields": [
    {
      "id": "employee.surname",
      "type": "grid",
      "page": 2,
      "x0": 132.48,
      "y": 360.39,
      "pitch": 15.84,
      "max_cells": 28,
      "font": "OfisSans",
      "size": 11.0,
      "align": "center",
      "_calibrated": true,
      "transform": "uppercase"
    },
    {
      "id": "employee.name",
      "type": "grid",
      "page": 2,
      "x0": 132.48,
      "y": 389.91,
      "pitch": 15.84,
      "max_cells": 28,
      "font": "OfisSans",
      "size": 11.0,
      "align": "center",
      "_calibrated": true,
      "transform": "uppercase"
    },
    {
      "id": "employee.patronymic",
      "type": "grid",
      "page": 2,
      "x0": 132.48,
      "y": 419.07,
      "pitch": 15.84,
      "max_cells": 28,
      "font": "OfisSans",
      "size": 11.0,
      "align": "center",
      "_calibrated": true,
      "transform": "uppercase"
    },
    {
      "id": "employee.citizenship",
      "type": "grid",
      "page": 2,
      "x0": 148.32,
      "y": 448.85,
      "pitch": 15.84,
      "max_cells": 27,
      "font": "OfisSans",
      "size": 11.0,
      "align": "center",
      "_calibrated": true,
      "transform": "uppercase"
    },
    {
      "id": "employee.birth.d",
      "type": "grid",
      "page": 2,
      "x0": 156.15,
      "y": 546.87,
      "pitch": 15.66,
      "max_cells": 2,
      "font": "OfisSans",
      "size": 11.0,
      "align": "center",
      "_calibrated": true,
      "formatter": "date_dd"
    },
    {
      "id": "employee.birth.m",
      "type": "grid",
      "page": 2,
      "x0": 215.1,
      "y": 546.87,
      "pitch": 15.48,
      "max_cells": 2,
      "font": "OfisSans",
      "size": 11.0,
      "align": "center",
      "_calibrated": true,
      "formatter": "date_mm"
    },
    {
      "id": "employee.birth.y",
      "type": "grid",
      "page": 2,
      "x0": 273.87,
      "y": 546.87,
      "pitch": 15.66,
      "max_cells": 4,
      "font": "OfisSans",
      "size": 11.0,
      "align": "center",
      "_calibrated": true,
      "formatter": "date_yyyy"
    },
    {
      "id": "employee.passport.series",
      "type": "grid",
      "page": 2,
      "x0": 82.44,
      "y": 630.39,
      "pitch": 15.84,
      "max_cells": 7,
      "font": "OfisSans",
      "size": 11.0,
      "align": "center",
      "_calibrated": true
    },
    {
      "id": "employee.passport.number",
      "type": "grid",
      "page": 2,
      "x0": 219.96,
      "y": 630.39,
      "pitch": 15.84,
      "max_cells": 9,
      "font": "OfisSans",
      "size": 11.0,
      "align": "center",
      "_calibrated": true
    },
    {
      "id": "employee.passport.issue.d",
      "type": "grid",
      "page": 2,
      "x0": 406.44,
      "y": 630.39,
      "pitch": 15.84,
      "max_cells": 2,
      "font": "OfisSans",
      "size": 11.0,
      "align": "center",
      "_calibrated": true,
      "formatter": "date_dd"
    },
    {
      "id": "employee.passport.issue.m",
      "type": "grid",
      "page": 2,
      "x0": 468.27,
      "y": 630.39,
      "pitch": 15.66,
      "max_cells": 2,
      "font": "OfisSans",
      "size": 11.0,
      "align": "center",
      "_calibrated": true,
      "formatter": "date_mm"
    },
    {
      "id": "employee.passport.issue.y",
      "type": "grid",
      "page": 2,
      "x0": 509.67,
      "y": 630.39,
      "pitch": 15.66,
      "max_cells": 4,
      "font": "OfisSans",
      "size": 11.0,
      "align": "center",
      "_calibrated": true,
      "formatter": "date_yyyy"
    },
    {
      "id": "employee.passport.issued_by",
      "type": "grid",
      "page": 2,
      "x0": 132.48,
      "y": 669.53,
      "pitch": 15.84,
      "max_cells": 28,
      "font": "OfisSans",
      "size": 11.0,
      "align": "center",
      "_calibrated": true,
      "transform": "uppercase"
    },
    {
      "id": "patent.series",
      "type": "grid",
      "page": 3,
      "x0": 86.76,
      "y": 133.95,
      "pitch": 15.84,
      "max_cells": 7,
      "font": "OfisSans",
      "size": 11.0,
      "align": "center",
      "_calibrated": true
    },
    {
      "id": "patent.number",
      "type": "grid",
      "page": 3,
      "x0": 223.92,
      "y": 133.95,
      "pitch": 15.84,
      "max_cells": 11,
      "font": "OfisSans",
      "size": 11.0,
      "align": "center",
      "_calibrated": true
    },
    {
      "id": "patent.issue.d",
      "type": "grid",
      "page": 3,
      "x0": 430.92,
      "y": 133.95,
      "pitch": 15.84,
      "max_cells": 2,
      "font": "OfisSans",
      "size": 11.0,
      "align": "center",
      "_calibrated": true,
      "formatter": "date_dd"
    },
    {
      "id": "patent.issue.m",
      "type": "grid",
      "page": 3,
      "x0": 472.32,
      "y": 133.95,
      "pitch": 15.84,
      "max_cells": 2,
      "font": "OfisSans",
      "size": 11.0,
      "align": "center",
      "_calibrated": true,
      "formatter": "date_mm"
    },
    {
      "id": "patent.issue.y",
      "type": "grid",
      "page": 3,
      "x0": 513.63,
      "y": 133.95,
      "pitch": 15.66,
      "max_cells": 4,
      "font": "OfisSans",
      "size": 11.0,
      "align": "center",
      "_calibrated": true,
      "formatter": "date_yyyy"
    },
    {
      "id": "patent.issued_by",
      "type": "grid",
      "page": 3,
      "x0": 138.24,
      "y": 170.31,
      "pitch": 15.84,
      "max_cells": 28,
      "font": "OfisSans",
      "size": 11.0,
      "align": "center",
      "_calibrated": true,
      "transform": "uppercase"
    },
    {
      "id": "patent.from.d",
      "type": "grid",
      "page": 3,
      "x0": 136.71,
      "y": 227.19,
      "pitch": 15.66,
      "max_cells": 2,
      "font": "OfisSans",
      "size": 11.0,
      "align": "center",
      "_calibrated": true,
      "formatter": "date_dd"
    },
    {
      "id": "patent.from.m",
      "type": "grid",
      "page": 3,
      "x0": 177.84,
      "y": 227.19,
      "pitch": 15.84,
      "max_cells": 2,
      "font": "OfisSans",
      "size": 11.0,
      "align": "center",
      "_calibrated": true,
      "formatter": "date_mm"
    },
    {
      "id": "patent.from.y",
      "type": "grid",
      "page": 3,
      "x0": 219.15,
      "y": 227.19,
      "pitch": 15.66,
      "max_cells": 4,
      "font": "OfisSans",
      "size": 11.0,
      "align": "center",
      "_calibrated": true,
      "formatter": "date_yyyy"
    },
    {
      "id": "patent.to.d",
      "type": "grid",
      "page": 3,
      "x0": 313.47,
      "y": 227.19,
      "pitch": 15.66,
      "max_cells": 2,
      "font": "OfisSans",
      "size": 11.0,
      "align": "center",
      "_calibrated": true,
      "formatter": "date_dd"
    },
    {
      "id": "patent.to.m",
      "type": "grid",
      "page": 3,
      "x0": 354.51,
      "y": 227.19,
      "pitch": 15.66,
      "max_cells": 2,
      "font": "OfisSans",
      "size": 11.0,
      "align": "center",
      "_calibrated": true,
      "formatter": "date_mm"
    },
    {
      "id": "patent.to.y",
      "type": "grid",
      "page": 3,
      "x0": 395.64,
      "y": 227.19,
      "pitch": 15.84,
      "max_cells": 4,
      "font": "OfisSans",
      "size": 11.0,
      "align": "center",
      "_calibrated": true,
      "formatter": "date_yyyy"
    },
    {
      "id": "employee.profession",
      "type": "grid",
      "page": 3,
      "x0": 50.4,
      "y": 489.0,
      "pitch": 15.84,
      "max_cells": 34,
      "font": "OfisSans",
      "size": 11.0,
      "align": "center",
      "transform": "uppercase",
      "_calibrated": true
    }
  ]
}